pyscaffoldext/cookiecutter/__init__.py
pyscaffoldext/cookiecutter/extension.py
pyscaffoldext_cookiecutter-0.1.dist-info/AUTHORS.rst
pyscaffoldext_cookiecutter-0.1.dist-info/LICENSE.txt
pyscaffoldext_cookiecutter-0.1.dist-info/METADATA
pyscaffoldext_cookiecutter-0.1.dist-info/WHEEL
pyscaffoldext_cookiecutter-0.1.dist-info/entry_points.txt
pyscaffoldext_cookiecutter-0.1.dist-info/top_level.txt
pyscaffoldext_cookiecutter-0.1.dist-info/RECORD
