Metadata-Version: 2.1
Name: pyscaffoldext-cookiecutter
Version: 0.1
Summary: Integration of Cookiecutter project templates into PyScaffold (see: https://github.com/cookiecutter/cookiecutter)
Home-page: https://github.com/pyscaffold/pyscaffoldext-cookiecutter/
Author: Anderson Bravalheri
Author-email: andersonbravalheri@gmail.com
License: MIT
Project-URL: Documentation, https://pyscaffoldext-custom-extension.readthedocs.io/
Project-URL: Source, https://github.com/pyscaffold/pyscaffoldext-cookiecutter/
Project-URL: Tracker, https://github.com/pyscaffold/pyscaffoldext-cookiecutter/issues
Project-URL: Download, https://pypi.org/project/pyscaffoldext-cookiecutter/#files
Platform: any
Classifier: Development Status :: 4 - Beta
Classifier: Programming Language :: Python
Requires-Dist: pyscaffold (<5.0a0,>=4.0b4)
Requires-Dist: cookiecutter
Requires-Dist: importlib-metadata ; python_version < "3.8"
Provides-Extra: testing
Requires-Dist: tox ; extra == 'testing'
Requires-Dist: pre-commit ; extra == 'testing'
Requires-Dist: setuptools-scm ; extra == 'testing'
Requires-Dist: virtualenv ; extra == 'testing'
Requires-Dist: configupdater ; extra == 'testing'
Requires-Dist: pytest ; extra == 'testing'
Requires-Dist: pytest-cov ; extra == 'testing'
Requires-Dist: pytest-xdist ; extra == 'testing'
